{
  "project_info": {
    "project_number": "993439670834",
    "firebase_url": "https://gastroventure-dd480.firebaseio.com",
    "project_id": "gastroventure-dd480",
    "storage_bucket": "gastroventure-dd480.appspot.com"
  },
  "client": [
    {
      "client_info": {
        "mobilesdk_app_id": "1:993439670834:android:f3983cf12472b930de522b",
        "android_client_info": {
          "package_name": "com.teamproject.gastroventure"
        }
      },
      "oauth_client": [
        {
          "client_id": "993439670834-2upfv28aegpumuprqrnnl3pu5v737t0c.apps.googleusercontent.com",
          "client_type": 1,
          "android_info": {
            "package_name": "com.teamproject.gastroventure",
            "certificate_hash": "825c24b10ce3f99f024d2beb18a49deb47d3ca6c"
          }
        },
        {
          "client_id": "993439670834-ujnmn7d8c7ebfms5c6msch1hn46mg5dc.apps.googleusercontent.com",
          "client_type": 3
        }
      ],
      "api_key": [
        {
          "current_key": "AIzaSyDzfElnHuS1-aCiiBPsKkERoHHRXFTA9uE"
        }
      ],
      "services": {
        "appinvite_service": {
          "other_platform_oauth_client": [
            {
              "client_id": "993439670834-ujnmn7d8c7ebfms5c6msch1hn46mg5dc.apps.googleusercontent.com",
              "client_type": 3
            }
          ]
        }
      }
    }
  ],
  "configuration_version": "1"
}